cubicweb_seo/__init__.py
cubicweb_seo/__pkginfo__.py
cubicweb_seo/views.py
cubicweb_seo/i18n/en.po
cubicweb_seo/i18n/es.po
cubicweb_seo/i18n/fr.po
cubicweb_seo-1.0.0.dist-info/METADATA
cubicweb_seo-1.0.0.dist-info/WHEEL
cubicweb_seo-1.0.0.dist-info/entry_points.txt
cubicweb_seo-1.0.0.dist-info/top_level.txt
cubicweb_seo-1.0.0.dist-info/RECORD
