Metadata-Version: 2.1
Name: cubicweb-seo
Version: 1.0.0
Summary: search engine optimisation with robotstxt and sitemaps
Home-page: https://forge.extranet.logilab.fr/cubicweb/cubes/cubicweb-seo
Author: LOGILAB S.A. (Paris, FRANCE)
Author-email: contact@logilab.fr
License: LGPL
Classifier: Environment :: Web Environment
Classifier: Framework :: CubicWeb
Classifier: Programming Language :: Python
Classifier: Programming Language :: JavaScript
Requires-Dist: cubicweb (<5.0.0,>=4.0.0)
Requires-Dist: cubicweb-web (<2.0.0,>=1.0.0)
